aiohttp_runner/__init__.py
aiohttp_runner/_calendar.py
aiohttp_runner/_gunicorn_http_runner.py
aiohttp_runner/_gunicorn_subprocess.py
aiohttp_runner/_http_runner.py
aiohttp_runner/_serialize.py
aiohttp_runner/_simple_http_runner.py
aiohttp_runner/_utils.py
aiohttp_runner/py.typed
aiohttp_runner-0.5.0.dist-info/WHEEL
aiohttp_runner-0.5.0.dist-info/METADATA
aiohttp_runner-0.5.0.dist-info/RECORD
