Metadata-Version: 2.1
Name: aiohttp-runner
Version: 0.5.0
Summary: Wraps aiohttp or gunicorn server for aiohttp application.
Author: xppt
Author-email: 21246102+xppt@users.noreply.github.com
Requires-Python: >=3.6,<4.0
Classifier: Programming Language :: Python :: 3
Classifier: Programming Language :: Python :: 3.6
Classifier: Programming Language :: Python :: 3.7
Classifier: Programming Language :: Python :: 3.8
Classifier: Programming Language :: Python :: 3.9
Provides-Extra: gunicorn
Requires-Dist: aiohttp (>=3,<4)
Requires-Dist: async-exit-stack (>=1,<2)
Requires-Dist: async_generator (>=1,<2)
